MANIFEST.in
README.txt
setup.py
docs/HISTORY.txt
docs/LICENSE.txt
src/silva/__init__.py
src/silva.core.upgrade.egg-info/PKG-INFO
src/silva.core.upgrade.egg-info/SOURCES.txt
src/silva.core.upgrade.egg-info/dependency_links.txt
src/silva.core.upgrade.egg-info/entry_points.txt
src/silva.core.upgrade.egg-info/namespace_packages.txt
src/silva.core.upgrade.egg-info/not-zip-safe
src/silva.core.upgrade.egg-info/requires.txt
src/silva.core.upgrade.egg-info/top_level.txt
src/silva/core/__init__.py
src/silva/core/upgrade/__init__.py
src/silva/core/upgrade/command.py
src/silva/core/upgrade/configure.zcml
src/silva/core/upgrade/localsite.py
src/silva/core/upgrade/silvaxml.py
src/silva/core/upgrade/upgrade.py
src/silva/core/upgrade/martiansupport/__init__.py
src/silva/core/upgrade/martiansupport/upgrader.py
src/silva/core/upgrade/tests/__init__.py
src/silva/core/upgrade/tests/test_upgrade.py
src/silva/core/upgrade/tests/test_upgrader_tags_filtering.py
src/silva/core/upgrade/upgrader/__init__.py
src/silva/core/upgrade/upgrader/upgrade_220.py
src/silva/core/upgrade/upgrader/upgrade_230.py
src/silva/core/upgrade/upgrader/upgrade_236.py
src/silva/core/upgrade/upgrader/upgrade_300.py
src/silva/core/upgrade/upgrader/upgrade_303.py
src/silva/core/upgrade/upgrader/tests/__init__.py
src/silva/core/upgrade/upgrader/tests/test_upgrader_file.py
src/silva/core/upgrade/upgrader/tests/test_upgrader_ghost.py
src/silva/core/upgrade/upgrader/tests/test_upgrader_hide_from_tocs.py
src/silva/core/upgrade/upgrader/tests/test_upgrader_image.py
src/silva/core/upgrade/upgrader/tests/test_upgrader_link.py