Metadata-Version: 1.1
Name: silva.core.upgrade
Version: 3.0.2
Summary: Upgrade between the different versions of Silva CMS
Home-page: https://github.com/silvacms/silva.core.upgrade
Author: Sylvain Viollon
Author-email: info@infrae.com
License: BSD
Keywords: silva core upgrade
Platform: UNKNOWN
Classifier: Framework :: Zope2
Classifier: Programming Language :: Python
Classifier: Topic :: Software Development :: Libraries :: Python Modules
Classifier: License :: OSI Approved :: BSD License
